mt/glm/__init__.py
mt/glm/linear.py
mt/glm/version.py
mtglm-0.1.202402250103.dist-info/LICENSE
mtglm-0.1.202402250103.dist-info/METADATA
mtglm-0.1.202402250103.dist-info/WHEEL
mtglm-0.1.202402250103.dist-info/top_level.txt
mtglm-0.1.202402250103.dist-info/RECORD
