Metadata-Version: 2.1
Name: mtglm
Version: 0.1.202402250103
Summary: Minh-Tri Pham's extra modules for dealing with GLM in Python
Author: ['Minh-Tri Pham']
License-File: LICENSE
Requires-Dist: pyglm
